tennyson/__init__.py
tennyson/cli.py
tennyson/commons.py
tennyson/config.py
tennyson/password.py
tennyson/printing.py
tennyson/safty.py
tennyson/vault.py
tennyson/viz.py
tennyson/static/diceware.txt
tennyson-0.0.4.dist-info/METADATA
tennyson-0.0.4.dist-info/WHEEL
tennyson-0.0.4.dist-info/entry_points.txt
tennyson-0.0.4.dist-info/top_level.txt
tennyson-0.0.4.dist-info/RECORD
