Metadata-Version: 2.4
Name: tennyson
Version: 0.0.4
Summary: Your package description
License: None
Requires-Python: >=3.8
Requires-Dist: boto3
Requires-Dist: click
Requires-Dist: hvac
Requires-Dist: psutil
Provides-Extra: dev
Requires-Dist: pytest>=7.0; extra == "dev"
Requires-Dist: build; extra == "dev"
Requires-Dist: setuptools; extra == "dev"
Requires-Dist: twine; extra == "dev"
Provides-Extra: test
Requires-Dist: pytest>=7.0; extra == "test"
